resources/__init__.py
src/__init__.py
src/cli.py
src/project.py
src/resource_schemas/__init__.py
src/resource_schemas/compute.py
src/resource_schemas/network.py
src/resource_schemas/project.py
src/resource_schemas/volume.py
src/service/__init__.py
src/service/compute/__init__.py
src/service/compute/instance.py
src/service/network/__init__.py
src/service/network/network.py
src/service/network/security_group.py
src/service/volume/__init__.py
src/service/volume/volume.py
src/util/__init__.py
src/util/constants.py
src/util/file_utils.py
src/util/http_helper.py
src/util/utils.py
ccpcli-0.7.dist-info/METADATA
ccpcli-0.7.dist-info/WHEEL
ccpcli-0.7.dist-info/entry_points.txt
ccpcli-0.7.dist-info/top_level.txt
ccpcli-0.7.dist-info/RECORD
