Metadata-Version: 2.1
Name: ccpcli
Version: 0.7
Summary: CCP cli
Author: Mani Keshari
Author-email: info@coredge.io
Requires-Dist: click
Requires-Dist: halo
Requires-Dist: tabulate
